NoobFramework/__init__.py
NoobFramework/decorators/__init__.py
NoobFramework/decorators/controller.py
NoobFramework/regex/__init__.py
NoobFramework/regex/regex_utils.py
NoobFramework/router/__init__.py
NoobFramework/router/load_controller.py
NoobFramework/router/router.py
NoobFramework/webob/__init__.py
NoobFramework/webob/acceptparse.py
NoobFramework/webob/byterange.py
NoobFramework/webob/cachecontrol.py
NoobFramework/webob/client.py
NoobFramework/webob/compat.py
NoobFramework/webob/cookies.py
NoobFramework/webob/datetime_utils.py
NoobFramework/webob/dec.py
NoobFramework/webob/descriptors.py
NoobFramework/webob/etag.py
NoobFramework/webob/exc.py
NoobFramework/webob/headers.py
NoobFramework/webob/multidict.py
NoobFramework/webob/request.py
NoobFramework/webob/response.py
NoobFramework/webob/static.py
NoobFramework/webob/util.py
NoobFramework-0.0.1.dist-info/LICENSE
NoobFramework-0.0.1.dist-info/METADATA
NoobFramework-0.0.1.dist-info/WHEEL
NoobFramework-0.0.1.dist-info/top_level.txt
NoobFramework-0.0.1.dist-info/RECORD
