Metadata-Version: 2.1
Name: NoobFramework
Version: 0.0.1
Summary: Web NoobFramework in python
Home-page: https://github.com/DhavalKapil/nooooooooooob
Author: Piyush Aggarwal
Author-email: piyush8311@gmail.com
License: UNKNOWN
Platform: UNKNOWN
Classifier: Programming Language :: Python :: 3
Classifier: License :: OSI Approved :: MIT License
Classifier: Operating System :: OS Independent
